{
  "image": "IMG_20250904_130410281_AE.jpg",
  "size": {
    "w": 2304,
    "h": 4096
  },
  "z_mm": 500,
  "conf_used": 0.15,
  "cauliflowers": [
    {
      "cls": 0,
      "name": "cauliflower",
      "conf": 0.86,
      "cx": 1073,
      "cy": 1992,
      "z": 500,
      "cx_norm": 0.4657,
      "cy_norm": 0.4863,
      "bbox": [
        833,
        1795,
        1331,
        2219
      ],
      "area": 82474
    },
    {
      "cls": 0,
      "name": "cauliflower",
      "conf": 0.837,
      "cx": 1578,
      "cy": 740,
      "z": 500,
      "cx_norm": 0.6849,
      "cy_norm": 0.1807,
      "bbox": [
        1475,
        566,
        1768,
        896
      ],
      "area": 48169
    },
    {
      "cls": 0,
      "name": "cauliflower",
      "conf": 0.169,
      "cx": 1821,
      "cy": 30,
      "z": 500,
      "cx_norm": 0.7904,
      "cy_norm": 0.0073,
      "bbox": [
        1840,
        2,
        1918,
        59
      ],
      "area": 2348
    },
    {
      "cls": 0,
      "name": "cauliflower",
      "conf": 0.151,
      "cx": 281,
      "cy": 444,
      "z": 500,
      "cx_norm": 0.122,
      "cy_norm": 0.1084,
      "bbox": [
        2,
        253,
        497,
        610
      ],
      "area": 102748
    }
  ],
  "robot": {
    "n_cauliflowers": 4,
    "cauliflowers": [
      {
        "x": 1073,
        "y": 1992,
        "z": 500,
        "conf": 0.86
      },
      {
        "x": 1578,
        "y": 740,
        "z": 500,
        "conf": 0.837
      },
      {
        "x": 1821,
        "y": 30,
        "z": 500,
        "conf": 0.169
      },
      {
        "x": 281,
        "y": 444,
        "z": 500,
        "conf": 0.151
      }
    ]
  }
}